pymodaq_plugins_signal_recovery/__init__.py
pymodaq_plugins_signal_recovery/utils.py
pymodaq_plugins_signal_recovery/daq_move_plugins/__init__.py
pymodaq_plugins_signal_recovery/daq_move_plugins/daq_move_Lockin_DSP7265.py
pymodaq_plugins_signal_recovery/daq_move_plugins/daq_move_Lockin_DSP7270.py
pymodaq_plugins_signal_recovery/daq_viewer_plugins/__init__.py
pymodaq_plugins_signal_recovery/daq_viewer_plugins/plugins_0D/__init__.py
pymodaq_plugins_signal_recovery/daq_viewer_plugins/plugins_0D/daq_0Dviewer_Lockin_DSP7265.py
pymodaq_plugins_signal_recovery/daq_viewer_plugins/plugins_0D/daq_0Dviewer_Lockin_DSP7270.py
pymodaq_plugins_signal_recovery/daq_viewer_plugins/plugins_1D/__init__.py
pymodaq_plugins_signal_recovery/daq_viewer_plugins/plugins_2D/__init__.py
pymodaq_plugins_signal_recovery/daq_viewer_plugins/plugins_ND/__init__.py
pymodaq_plugins_signal_recovery/hardware/__init__.py
pymodaq_plugins_signal_recovery/hardware/dsp_7265_thread_safe.py
pymodaq_plugins_signal_recovery/hardware/utils.py
pymodaq_plugins_signal_recovery/resources/VERSION
pymodaq_plugins_signal_recovery/resources/__init__.py
pymodaq_plugins_signal_recovery/resources/config_template.toml
pymodaq_plugins_signal_recovery-0.1.0.dist-info/LICENSE
pymodaq_plugins_signal_recovery-0.1.0.dist-info/METADATA
pymodaq_plugins_signal_recovery-0.1.0.dist-info/WHEEL
pymodaq_plugins_signal_recovery-0.1.0.dist-info/entry_points.txt
pymodaq_plugins_signal_recovery-0.1.0.dist-info/top_level.txt
pymodaq_plugins_signal_recovery-0.1.0.dist-info/RECORD
